[
  {
    "name": "Weekend Getaway - New York",
    "price": 60000,
    "type": "Vacation",
    "description": "Lorem ipsum dolor sit amet, ne vis quem graeco consetetur, id eam doming admodum epicurei. ",
    "tags": [
      "Vacation",
      "Travel",
      "New York",
      "Flight",
      "Vacation Packages"
    ],
    "imageURL": "/assets/img/rewards/weekend1.jpg",
    "meta": {
      "purchased": 1,
      "selected": 1
    }
  },
  {
    "name": "Weekend Getaway - Minneapolis",
    "price": 60000,
    "type": "Vacation",
    "description": "Lorem ipsum dolor sit amet, ne vis quem graeco consetetur, id eam doming admodum epicurei. ",
    "tags": [
      "Vacation",
      "Travel",
      "Minneapolis",
      "Flight",
      "Vacation Packages"
    ],
    "imageURL": "/assets/img/rewards/weekend2.jpg",
    "meta": {
      "purchased": 1,
      "selected": 1
    }
  },
  {
    "name": "Weekend Getaway - Boston",
    "price": 60000,
    "type": "Vacation",
    "description": "Lorem ipsum dolor sit amet, ne vis quem graeco consetetur, id eam doming admodum epicurei. ",
    "tags": [
      "Vacation",
      "Travel",
      "Boston",
      "Flight",
      "Vacation Packages"
    ],
    "imageURL": "/assets/img/rewards/weekend3.jpg",
    "meta": {
      "purchased": 1,
      "selected": 1
    }
  },
  {
    "name": "$5 Amazon",
    "price": 250,
    "type": "Gift Card",
    "description": "Lorem ipsum dolor sit amet, ne vis quem graeco consetetur, id eam doming admodum epicurei. ",
    "tags": [
      "Gift Card",
      "Gift Cards",
      "Shopping",
      "Amazon"
    ],
    "imageURL": "/assets/img/rewards/amazon.jpeg",
    "meta": {
      "purchased": 1,
      "selected": 1
    }
  },
  {
    "name": "$10 Amazon",
    "price": 500,
    "type": "Gift Card",
    "description": "Lorem ipsum dolor sit amet, ne vis quem graeco consetetur, id eam doming admodum epicurei. ",
    "tags": [
      "Gift Card",
      "Gift Cards",
      "Shopping",
      "Amazon"
    ],
    "imageURL": "/assets/img/rewards/amazon.jpeg",
    "meta": {
      "purchased": 1,
      "selected": 1
    }
  },
  {
    "name": "$20 Amazon",
    "price": 1000,
    "type": "Gift Card",
    "description": "Lorem ipsum dolor sit amet, ne vis quem graeco consetetur, id eam doming admodum epicurei. ",
    "tags": [
      "Gift Card",
      "Gift Cards",
      "Shopping",
      "Amazon"
    ],
    "imageURL": "/assets/img/rewards/amazon.jpeg",
    "meta": {
      "purchased": 1,
      "selected": 1
    }
  },
  {
    "name": "1-Night Hotel Stay",
    "price": 10000,
    "type": "Voucher",
    "description": "Lorem ipsum dolor sit amet, ne vis quem graeco consetetur, id eam doming admodum epicurei. ",
    "tags": [
      "Voucher",
      "Travel",
      "Hotel",
      "Vacation Packages"
    ],
    "imageURL": "/assets/img/rewards/hotel.jpg",
    "meta": {
      "purchased": 1,
      "selected": 1
    }
  },
  {
    "name": "2-Night Hotel Stay",
    "price": 20000,
    "type": "Voucher",
    "description": "Lorem ipsum dolor sit amet, ne vis quem graeco consetetur, id eam doming admodum epicurei. ",
    "tags": [
      "Voucher",
      "Travel",
      "Hotel",
      "Vacation Packages"
    ],
    "imageURL": "/assets/img/rewards/hotel.jpg",
    "meta": {
      "purchased": 1,
      "selected": 1
    }
  },
  {
    "name": "$100 Airline Voucher",
    "price": 5000,
    "type": "Gift Card",
    "description": "Lorem ipsum dolor sit amet, ne vis quem graeco consetetur, id eam doming admodum epicurei. ",
    "tags": [
      "Voucher",
      "Travel",
      "Flight",
      "Vacation Packages"
    ],
    "imageURL": "/assets/img/rewards/airline.jpg",
    "meta": {
      "purchased": 1,
      "selected": 1
    }
  },
  {
    "name": "$200 Airline Voucher",
    "price": 10000,
    "type": "Gift Card",
    "description": "Lorem ipsum dolor sit amet, ne vis quem graeco consetetur, id eam doming admodum epicurei. ",
    "tags": [
      "Voucher",
      "Travel",
      "Flight",
      "Vacation Packages"
    ],
    "imageURL": "/assets/img/rewards/airline.jpg",
    "meta": {
      "purchased": 1,
      "selected": 1
    }
  },
  {
    "name": "3-Month Gym Membership",
    "price": 7500,
    "type": "Fitness",
    "description": "Lorem ipsum dolor sit amet, ne vis quem graeco consetetur, id eam doming admodum epicurei. ",
    "tags": [
      "Fitness",
      "Gym",
      "Membership",
      "Workout",
      "Gym Membership"
    ],
    "imageURL": "/assets/img/rewards/gym.jpg",
    "meta": {
      "purchased": 1,
      "selected": 1
    }
  },
  {
    "name": "6-Month Gym Membership",
    "price": 15000,
    "type": "Fitness",
    "description": "Lorem ipsum dolor sit amet, ne vis quem graeco consetetur, id eam doming admodum epicurei. ",
    "tags": [
      "Fitness",
      "Gym",
      "Membership",
      "Workout",
      "Gym Membership"
    ],
    "imageURL": "/assets/img/rewards/gym.jpg",
    "meta": {
      "purchased": 1,
      "selected": 1
    }
  },
  {
    "name": "9-Month Gym Membership",
    "price": 22500,
    "type": "Fitness",
    "description": "Lorem ipsum dolor sit amet, ne vis quem graeco consetetur, id eam doming admodum epicurei. ",
    "tags": [
      "Fitness",
      "Gym",
      "Membership",
      "Workout",
      "Gym Membership"
    ],
    "imageURL": "/assets/img/rewards/gym.jpg",
    "meta": {
      "purchased": 1,
      "selected": 1
    }
  },
  {
    "name": "12-Month Gym Membership",
    "price": 30000,
    "type": "Fitness",
    "description": "Lorem ipsum dolor sit amet, ne vis quem graeco consetetur, id eam doming admodum epicurei. ",
    "tags": [
      "Fitness",
      "Gym",
      "Membership",
      "Workout",
      "Gym Membership"
    ],
    "imageURL": "/assets/img/rewards/gym.jpg",
    "meta": {
      "purchased": 1,
      "selected": 1
    }
  },
  {
    "name": "$5 Trader Joes",
    "price": 250,
    "type": "Gift Card",
    "description": "Lorem ipsum dolor sit amet, ne vis quem graeco consetetur, id eam doming admodum epicurei. ",
    "tags": [
      "Gift Card",
      "Gift Cards",
      "Shopping",
      "Food",
      "Grocery",
      "Groceries"
    ],
    "imageURL": "../../../assets/img/rewards/tjs.jpg",
    "meta": {
      "purchased": 1,
      "selected": 1
    }
  },
  {
    "name": "$10 Trader Joes",
    "price": 500,
    "type": "Gift Card",
    "description": "Lorem ipsum dolor sit amet, ne vis quem graeco consetetur, id eam doming admodum epicurei. ",
    "tags": [
      "Gift Card",
      "Gift Cards",
      "Shopping",
      "Food",
      "Grocery",
      "Groceries"
    ],
    "imageURL": "../../../assets/img/rewards/tjs.jpg",
    "meta": {
      "purchased": 1,
      "selected": 1
    }
  },
  {
    "name": "$20 Trader Joes",
    "price": 1000,
    "type": "Gift Card",
    "description": "Lorem ipsum dolor sit amet, ne vis quem graeco consetetur, id eam doming admodum epicurei. ",
    "tags": [
      "Gift Card",
      "Gift Cards",
      "Shopping",
      "Food",
      "Grocery",
      "Groceries"
    ],
    "imageURL": "../../../assets/img/rewards/tjs.jpg",
    "meta": {
      "purchased": 1,
      "selected": 1
    }
  },
  {
    "name": "$5 Walmart",
    "price": 250,
    "type": "Gift Card",
    "description": "Lorem ipsum dolor sit amet, ne vis quem graeco consetetur, id eam doming admodum epicurei. ",
    "tags": [
      "Gift Card",
      "Gift Cards",
      "Shopping",
      "Food",
      "Walmart",
      "Everyday",
      "Items"
    ],
    "imageURL": "../../../assets/img/rewards/walmart.jpg",
    "meta": {
      "purchased": 1,
      "selected": 1
    }
  },
  {
    "name": "$10 Walmart",
    "price": 500,
    "type": "Gift Card",
    "description": "Lorem ipsum dolor sit amet, ne vis quem graeco consetetur, id eam doming admodum epicurei. ",
    "tags": [
      "Gift Card",
      "Gift Cards",
      "Shopping",
      "Food",
      "Walmart",
      "Everyday",
      "Items"
    ],
    "imageURL": "../../../assets/img/rewards/walmart.jpg",
    "meta": {
      "purchased": 1,
      "selected": 1
    }
  },
  {
    "name": "$20 Walmart",
    "price": 1000,
    "type": "Gift Card",
    "description": "Lorem ipsum dolor sit amet, ne vis quem graeco consetetur, id eam doming admodum epicurei. ",
    "tags": [
      "Gift Card",
      "Gift Cards",
      "Shopping",
      "Food",
      "Walmart",
      "Everyday",
      "Items"
    ],
    "imageURL": "/assets/img/rewards/walmart.jpg",
    "meta": {
      "purchased": 1,
      "selected": 1
    }
  },
  {
    "name": "$5 BP Gas",
    "price": 250,
    "type": "Gift Card",
    "description": "Lorem ipsum dolor sit amet, ne vis quem graeco consetetur, id eam doming admodum epicurei. ",
    "tags": [
      "Gift Card",
      "Gift Cards",
      "Shopping",
      "Travel",
      "Gasoline",
      "Gas"
    ],
    "imageURL": "../../../assets/img/rewards/bp.jpg",
    "meta": {
      "purchased": 1,
      "selected": 1
    }
  },
  {
    "name": "$10 BP Gas",
    "price": 500,
    "type": "Gift Card",
    "description": "Lorem ipsum dolor sit amet, ne vis quem graeco consetetur, id eam doming admodum epicurei. ",
    "tags": [
      "Gift Card",
      "Gift Cards",
      "Shopping",
      "Travel",
      "Gasoline",
      "Gas"
    ],
    "imageURL": "../../../assets/img/rewards/bp.jpg",
    "meta": {
      "purchased": 1,
      "selected": 1
    }
  },
  {
    "name": "$20 BP Gas",
    "price": 1000,
    "type": "Gift Card",
    "description": "Lorem ipsum dolor sit amet, ne vis quem graeco consetetur, id eam doming admodum epicurei. ",
    "tags": [
      "Gift Card",
      "Gift Cards",
      "Shopping",
      "Travel",
      "Gasoline",
      "Gas"
    ],
    "imageURL": "../../../assets/img/rewards/bp.jpg",
    "meta": {
      "purchased": 1,
      "selected": 1
    }
  },
  {
    "name": "One-Month Free Metro Card",
    "price": 4250,
    "type": "Voucher",
    "description": "Lorem ipsum dolor sit amet, ne vis quem graeco consetetur, id eam doming admodum epicurei. ",
    "tags": [
      "Travel",
      "Commuting",
      "Voucher",
      "Public Transport"
    ],
    "imageURL": "../../../assets/img/rewards/metro.jpg",
    "meta": {
      "purchased": 1,
      "selected": 1
    }
  },
  {
    "name": "Apple iPad Mini 4",
    "price": 22500,
    "type": "Electronics",
    "description": "Lorem ipsum dolor sit amet, ne vis quem graeco consetetur, id eam doming admodum epicurei. ",
    "tags": [
      "Apple",
      "Tablet",
      "Electronics",
      "Computer",
      "Mobile",
      "iPad"
    ],
    "imageURL": "../../../assets/img/rewards/ipad-mini-4.jpeg",
    "meta": {
      "purchased": 1,
      "selected": 1
    }
  },
  {
    "name": "Apple iPad",
    "price": 17500,
    "type": "Electronics",
    "description": "Lorem ipsum dolor sit amet, ne vis quem graeco consetetur, id eam doming admodum epicurei. ",
    "tags": [
      "Apple",
      "Tablet",
      "Electronics",
      "Computer",
      "Mobile",
      "iPad"
    ],
    "imageURL": "../../../assets/img/rewards/ipad-ipad.jpeg",
    "meta": {
      "purchased": 1,
      "selected": 1
    }
  },
  {
    "name": "10.5-inch Apple iPad Pro",
    "price": 33750,
    "type": "Electronics",
    "description": "Lorem ipsum dolor sit amet, ne vis quem graeco consetetur, id eam doming admodum epicurei. ",
    "tags": [
      "Apple",
      "Tablet",
      "Electronics",
      "Computer",
      "Mobile",
      "iPad"
    ],
    "imageURL": "../../../assets/img/rewards/ipad-pro-10in.jpeg",
    "meta": {
      "purchased": 1,
      "selected": 1
    }
  },
  {
    "name": "11-inch Apple iPad Pro",
    "price": 42500,
    "type": "Electronics",
    "description": "Lorem ipsum dolor sit amet, ne vis quem graeco consetetur, id eam doming admodum epicurei. ",
    "tags": [
      "Apple",
      "Tablet",
      "Electronics",
      "Computer",
      "Mobile",
      "iPad"
    ],
    "imageURL": "../../../assets/img/rewards/ipad-pro-11in.jpeg",
    "meta": {
      "purchased": 1,
      "selected": 1
    }
  },
  {
    "name": "12.9-inch Apple iPad Pro",
    "price": 55000,
    "type": "Electronics",
    "description": "Lorem ipsum dolor sit amet, ne vis quem graeco consetetur, id eam doming admodum epicurei. ",
    "tags": [
      "Apple",
      "Tablet",
      "Electronics",
      "Computer",
      "Mobile",
      "iPad"
    ],
    "imageURL": "../../../assets/img/rewards/ipad-pro-12in.jpeg",
    "meta": {
      "purchased": 1,
      "selected": 1
    }
  },
  {
    "name": "Apple Watch Series 4",
    "price": 21250,
    "type": "Electronics",
    "description": "Lorem ipsum dolor sit amet, ne vis quem graeco consetetur, id eam doming admodum epicurei. ",
    "tags": [
      "Apple",
      "Tablet",
      "Electronics",
      "Computer",
      "Mobile",
      "Watch"
    ],
    "imageURL": "../../../assets/img/rewards/watch-s4.jpeg",
    "meta": {
      "purchased": 1,
      "selected": 1
    }
  },
  {
    "name": "Apple Watch Series 3",
    "price": 20200,
    "type": "Electronics",
    "description": "Lorem ipsum dolor sit amet, ne vis quem graeco consetetur, id eam doming admodum epicurei. ",
    "tags": [
      "Apple",
      "Tablet",
      "Electronics",
      "Computer",
      "Mobile",
      "Watch"
    ],
    "imageURL": "../../../assets/img/rewards/watch-s3.jpg",
    "meta": {
      "purchased": 1,
      "selected": 1
    }
  },
  {
    "name": "Fitbit Charge 3",
    "price": 7000,
    "type": "Electronics",
    "description": "Lorem ipsum dolor sit amet, ne vis quem graeco consetetur, id eam doming admodum epicurei. ",
    "tags": [
      "Fitbit",
      "Electronics",
      "Computer",
      "Mobile",
      "Watch"
    ],
    "imageURL": "../../../assets/img/rewards/fitbit-charge3.png",
    "meta": {
      "purchased": 1,
      "selected": 1
    }
  },
  {
    "name": "Fitbit Flex 2",
    "price": 2750,
    "type": "Electronics",
    "description": "Lorem ipsum dolor sit amet, ne vis quem graeco consetetur, id eam doming admodum epicurei. ",
    "tags": [
      "Fitbit",
      "Electronics",
      "Computer",
      "Mobile",
      "Watch"
    ],
    "imageURL": "../../../assets/img/rewards/fitbit-flex2.jpg",
    "meta": {
      "purchased": 1,
      "selected": 1
    }
  },
  {
    "name": "Fitbit Versa",
    "price": 11000,
    "type": "Electronics",
    "description": "Lorem ipsum dolor sit amet, ne vis quem graeco consetetur, id eam doming admodum epicurei. ",
    "tags": [
      "Fitbit",
      "Electronics",
      "Computer",
      "Mobile",
      "Watch"
    ],
    "imageURL": "../../../assets/img/rewards/fitbit-versa.png",
    "meta": {
      "purchased": 1,
      "selected": 1
    }
  },
  {
    "name": "Fitbit Ionic",
    "price": 9500,
    "type": "Electronics",
    "description": "Lorem ipsum dolor sit amet, ne vis quem graeco consetetur, id eam doming admodum epicurei. ",
    "tags": [
      "Fitbit",
      "Electronics",
      "Computer",
      "Mobile",
      "Watch"
    ],
    "imageURL": "../../../assets/img/rewards/fitbit-ionic.png",
    "meta": {
      "purchased": 1,
      "selected": 1
    }
  },
  {
    "name": "$5 Dunkin Donuts",
    "price": 275,
    "type": "Gift Card",
    "description": "Lorem ipsum dolor sit amet, ne vis quem graeco consetetur, id eam doming admodum epicurei. ",
    "tags": [
      "Dunkin Donuts",
      "Coffee",
      "Gift Card",
      "Gift Cards",
      "Fast Food"
    ],
    "imageURL": "../../../assets/img/rewards/dunkin.jpg",
    "meta": {
      "purchased": 1,
      "selected": 1
    }
  },
  {
    "name": "$10 Dunkin Donuts",
    "price": 550,
    "type": "Gift Card",
    "description": "Lorem ipsum dolor sit amet, ne vis quem graeco consetetur, id eam doming admodum epicurei. ",
    "tags": [
      "Dunkin Donuts",
      "Coffee",
      "Gift Card",
      "Gift Cards",
      "Fast Food"
    ],
    "imageURL": "../../../assets/img/rewards/dunkin.jpg",
    "meta": {
      "purchased": 1,
      "selected": 1
    }
  },
  {
    "name": "$20 Dunkin Donuts",
    "price": 1000,
    "type": "Gift Card",
    "description": "Lorem ipsum dolor sit amet, ne vis quem graeco consetetur, id eam doming admodum epicurei. ",
    "tags": [
      "Dunkin Donuts",
      "Coffee",
      "Gift Card",
      "Gift Cards",
      "Fast Food"
    ],
    "imageURL": "../../../assets/img/rewards/dunkin.jpg",
    "meta": {
      "purchased": 1,
      "selected": 1
    }
  },
  {
    "name": "$5 Starbucks",
    "price": 275,
    "type": "Gift Card",
    "description": "Lorem ipsum dolor sit amet, ne vis quem graeco consetetur, id eam doming admodum epicurei. ",
    "tags": [
      "Coffee",
      "Starbucks",
      "Gift Card",
      "Gift Cards",
      "Fast Food"
    ],
    "imageURL": "../../../assets/img/rewards/starbucks.png",
    "meta": {
      "purchased": 1,
      "selected": 1
    }
  },
  {
    "name": "$10 Starbucks",
    "price": 550,
    "type": "Gift Card",
    "description": "Lorem ipsum dolor sit amet, ne vis quem graeco consetetur, id eam doming admodum epicurei. ",
    "tags": [
      "Coffee",
      "Starbucks",
      "Gift Card",
      "Gift Cards",
      "Fast Food"
    ],
    "imageURL": "../../../assets/img/rewards/starbucks.png",
    "meta": {
      "purchased": 1,
      "selected": 1
    }
  },
  {
    "name": "$20 Starbucks",
    "price": 1000,
    "type": "Gift Card",
    "description": "Lorem ipsum dolor sit amet, ne vis quem graeco consetetur, id eam doming admodum epicurei. ",
    "tags": [
      "Coffee",
      "Starbucks",
      "Gift Card",
      "Gift Cards",
      "Fast Food"
    ],
    "imageURL": "../../../assets/img/rewards/starbucks.png",
    "meta": {
      "purchased": 1,
      "selected": 1
    }
  },
  {
    "name": "$5 Tim Hortons",
    "price": 275,
    "type": "Gift Card",
    "description": "Lorem ipsum dolor sit amet, ne vis quem graeco consetetur, id eam doming admodum epicurei. ",
    "tags": [
      "Coffee",
      "Tim Hortons",
      "Gift Card",
      "Gift Cards",
      "Fast Food"
    ],
    "imageURL": "../../../assets/img/rewards/tim-hortons.jpeg",
    "meta": {
      "purchased": 1,
      "selected": 1
    }
  },
  {
    "name": "$10 Tim Hortons",
    "price": 550,
    "type": "Gift Card",
    "description": "Lorem ipsum dolor sit amet, ne vis quem graeco consetetur, id eam doming admodum epicurei. ",
    "tags": [
      "Coffee",
      "Tim Hortons",
      "Gift Card",
      "Gift Cards",
      "Fast Food"
    ],
    "imageURL": "../../../assets/img/rewards/tim-hortons.jpeg",
    "meta": {
      "purchased": 1,
      "selected": 1
    }
  },
  {
    "name": "$20 Tim Hortons",
    "price": 1000,
    "type": "Gift Card",
    "description": "Lorem ipsum dolor sit amet, ne vis quem graeco consetetur, id eam doming admodum epicurei. ",
    "tags": [
      "Coffee",
      "Tim Hortons",
      "Gift Card",
      "Gift Cards",
      "Fast Food"
    ],
    "imageURL": "../../../assets/img/rewards/tim-hortons.jpeg",
    "meta": {
      "purchased": 1,
      "selected": 1
    }
  },
  {
    "name": "$5 McDonalds",
    "price": 275,
    "type": "Gift Card",
    "description": "Lorem ipsum dolor sit amet, ne vis quem graeco consetetur, id eam doming admodum epicurei. ",
    "tags": [
      "Burgers",
      "Fries",
      "McDonalds",
      "Gift Card",
      "Gift Cards",
      "Fast Food"
    ],
    "imageURL": "../../../assets/img/rewards/mcdonalds.jpg",
    "meta": {
      "purchased": 1,
      "selected": 1
    }
  },
  {
    "name": "$10 McDonalds",
    "price": 550,
    "type": "Gift Card",
    "description": "Lorem ipsum dolor sit amet, ne vis quem graeco consetetur, id eam doming admodum epicurei. ",
    "tags": [
      "Burgers",
      "Fries",
      "McDonalds",
      "Gift Card",
      "Gift Cards",
      "Fast Food"
    ],
    "imageURL": "../../../assets/img/rewards/mcdonalds.jpg",
    "meta": {
      "purchased": 1,
      "selected": 1
    }
  },
  {
    "name": "$20 McDonalds",
    "price": 1000,
    "type": "Gift Card",
    "description": "Lorem ipsum dolor sit amet, ne vis quem graeco consetetur, id eam doming admodum epicurei. ",
    "tags": [
      "Burgers",
      "Fries",
      "McDonalds",
      "Gift Card",
      "Gift Cards",
      "Fast Food"
    ],
    "imageURL": "../../../assets/img/rewards/mcdonalds.jpg",
    "meta": {
      "purchased": 1,
      "selected": 1
    }
  },
  {
    "name": "$5 Arby's",
    "price": 275,
    "type": "Gift Card",
    "description": "Lorem ipsum dolor sit amet, ne vis quem graeco consetetur, id eam doming admodum epicurei. ",
    "tags": [
      "Sandwiches",
      "Fries",
      "Arby's",
      "Gift Card",
      "Gift Cards",
      "Fast Food"
    ],
    "imageURL": "../../../assets/img/rewards/arbys.jpg",
    "meta": {
      "purchased": 1,
      "selected": 1
    }
  },
  {
    "name": "$10 Arby's",
    "price": 550,
    "type": "Gift Card",
    "description": "Lorem ipsum dolor sit amet, ne vis quem graeco consetetur, id eam doming admodum epicurei. ",
    "tags": [
      "Sandwiches",
      "Fries",
      "Arby's",
      "Gift Card",
      "Gift Cards",
      "Fast Food"
    ],
    "imageURL": "../../../assets/img/rewards/arbys.jpg",
    "meta": {
      "purchased": 1,
      "selected": 1
    }
  },
  {
    "name": "$20 Arby's",
    "price": 1000,
    "type": "Gift Card",
    "description": "Lorem ipsum dolor sit amet, ne vis quem graeco consetetur, id eam doming admodum epicurei. ",
    "tags": [
      "Sandwiches",
      "Fries",
      "Arby's",
      "Gift Card",
      "Gift Cards",
      "Fast Food"
    ],
    "imageURL": "../../../assets/img/rewards/arbys.jpg",
    "meta": {
      "purchased": 1,
      "selected": 1
    }
  },
  {
    "name": "$5 Subway",
    "price": 275,
    "type": "Gift Card",
    "description": "Lorem ipsum dolor sit amet, ne vis quem graeco consetetur, id eam doming admodum epicurei. ",
    "tags": [
      "Sandwiches",
      "Subway",
      "Gift Card",
      "Gift Cards",
      "Fast Food"
    ],
    "imageURL": "../../../assets/img/rewards/subway.jpg",
    "meta": {
      "purchased": 1,
      "selected": 1
    }
  },
  {
    "name": "$10 Subway",
    "price": 550,
    "type": "Gift Card",
    "description": "Lorem ipsum dolor sit amet, ne vis quem graeco consetetur, id eam doming admodum epicurei. ",
    "tags": [
      "Sandwiches",
      "Subway",
      "Gift Card",
      "Gift Cards",
      "Fast Food"
    ],
    "imageURL": "../../../assets/img/rewards/subway.jpg",
    "meta": {
      "purchased": 1,
      "selected": 1
    }
  },
  {
    "name": "$20 Subway",
    "price": 1000,
    "type": "Gift Card",
    "description": "Lorem ipsum dolor sit amet, ne vis quem graeco consetetur, id eam doming admodum epicurei. ",
    "tags": [
      "Sandwiches",
      "Subway",
      "Gift Card",
      "Gift Cards",
      "Fast Food"
    ],
    "imageURL": "../../../assets/img/rewards/subway.jpg",
    "meta": {
      "purchased": 1,
      "selected": 1
    }
  },
  {
    "name": "$5 Uber",
    "price": 275,
    "type": "Gift Card",
    "description": "Lorem ipsum dolor sit amet, ne vis quem graeco consetetur, id eam doming admodum epicurei. ",
    "tags": [
      "Ride Sharing",
      "Travel",
      "Transportation",
      "Transport",
      "Car",
      "Uber",
      "Gift Card",
      "Gift Cards"
    ],
    "imageURL": "../../../assets/img/rewards/uber.jpg",
    "meta": {
      "purchased": 1,
      "selected": 1
    }
  },
  {
    "name": "$10 Uber",
    "price": 550,
    "type": "Gift Card",
    "description": "Lorem ipsum dolor sit amet, ne vis quem graeco consetetur, id eam doming admodum epicurei. ",
    "tags": [
      "Ride Sharing",
      "Travel",
      "Transportation",
      "Transport",
      "Car",
      "Uber",
      "Gift Card",
      "Gift Cards"
    ],
    "imageURL": "../../../assets/img/rewards/uber.jpg",
    "meta": {
      "purchased": 1,
      "selected": 1
    }
  },
  {
    "name": "$20 Uber",
    "price": 1000,
    "type": "Gift Card",
    "description": "Lorem ipsum dolor sit amet, ne vis quem graeco consetetur, id eam doming admodum epicurei. ",
    "tags": [
      "Ride Sharing",
      "Travel",
      "Transportation",
      "Transport",
      "Car",
      "Uber",
      "Gift Card",
      "Gift Cards"
    ],
    "imageURL": "../../../assets/img/rewards/uber.jpg",
    "meta": {
      "purchased": 1,
      "selected": 1
    }
  },
  {
    "name": "$5 Lyft",
    "price": 250,
    "type": "Gift Card",
    "description": "Lorem ipsum dolor sit amet, ne vis quem graeco consetetur, id eam doming admodum epicurei. ",
    "tags": [
      "Ride Sharing",
      "Travel",
      "Transportation",
      "Transport",
      "Car",
      "Lyft",
      "Gift Card",
      "Gift Cards"
    ],
    "imageURL": "../../../assets/img/rewards/lyft.png",
    "meta": {
      "purchased": 1,
      "selected": 1
    }
  },
  {
    "name": "$10 Lyft",
    "price": 500,
    "type": "Gift Card",
    "description": "Lorem ipsum dolor sit amet, ne vis quem graeco consetetur, id eam doming admodum epicurei. ",
    "tags": [
      "Ride Sharing",
      "Travel",
      "Transportation",
      "Transport",
      "Car",
      "Lyft",
      "Gift Card",
      "Gift Cards"
    ],
    "imageURL": "../../../assets/img/rewards/lyft.png",
    "meta": {
      "purchased": 1,
      "selected": 1
    }
  },
  {
    "name": "$20 Lyft",
    "price": 1000,
    "type": "Gift Card",
    "description": "Lorem ipsum dolor sit amet, ne vis quem graeco consetetur, id eam doming admodum epicurei. ",
    "tags": [
      "Ride Sharing",
      "Travel",
      "Transportation",
      "Transport",
      "Car",
      "Lyft",
      "Gift Card",
      "Gift Cards"
    ],
    "imageURL": "../../../assets/img/rewards/lyft.png",
    "meta": {
      "purchased": 1,
      "selected": 1
    }
  },
  {
    "name": "$5 Holiday Gas",
    "price": 250,
    "type": "Gift Card",
    "description": "Lorem ipsum dolor sit amet, ne vis quem graeco consetetur, id eam doming admodum epicurei. ",
    "tags": [
      "Gift Card",
      "Gift Cards",
      "Holiday",
      "Car",
      "Transportation",
      "Transport",
      "Shopping",
      "Travel",
      "Gasoline",
      "Gas"
    ],
    "imageURL": "../../../assets/img/rewards/holiday.jpeg",
    "meta": {
      "purchased": 1,
      "selected": 1
    }
  },
  {
    "name": "$10 Holiday Gas",
    "price": 500,
    "type": "Gift Card",
    "description": "Lorem ipsum dolor sit amet, ne vis quem graeco consetetur, id eam doming admodum epicurei. ",
    "tags": [
      "Gift Card",
      "Gift Cards",
      "Holiday",
      "Car",
      "Transportation",
      "Transport",
      "Shopping",
      "Travel",
      "Gasoline",
      "Gas"
    ],
    "imageURL": "../../../assets/img/rewards/holiday.jpeg",
    "meta": {
      "purchased": 1,
      "selected": 1
    }
  },
  {
    "name": "$20 Holiday Gas",
    "price": 1000,
    "type": "Gift Card",
    "description": "Lorem ipsum dolor sit amet, ne vis quem graeco consetetur, id eam doming admodum epicurei. ",
    "tags": [
      "Gift Card",
      "Gift Cards",
      "Holiday",
      "Car",
      "Transportation",
      "Transport",
      "Shopping",
      "Travel",
      "Gasoline",
      "Gas"
    ],
    "imageURL": "../../../assets/img/rewards/holiday.jpeg",
    "meta": {
      "purchased": 1,
      "selected": 1
    }
  }
]